sonarcloud_report/__init__.py
sonarcloud_report/__main__.py
sonarcloud_report/client.py
sonarcloud_report/generate_sonarcloud_project_report.py
sonarcloud_report/logger_manager.py
sonarcloud_report/quality_gate.py
sonarcloud_report/run.py
sonarcloud_report/template_manager.py
sonarcloud_report/tools.py
sonarcloud_report/templates/sonarcloud_report.j2
lupin_sonarcloud_report-1.0.2.dist-info/LICENCE
lupin_sonarcloud_report-1.0.2.dist-info/METADATA
lupin_sonarcloud_report-1.0.2.dist-info/WHEEL
lupin_sonarcloud_report-1.0.2.dist-info/entry_points.txt
lupin_sonarcloud_report-1.0.2.dist-info/top_level.txt
lupin_sonarcloud_report-1.0.2.dist-info/RECORD
