Metadata-Version: 2.1
Name: lupin_sonarcloud_report
Version: 1.0.2
Summary: Tool used to generate a report about the latest SonarCloud analysis of a project.
Author-email: LupinDental <contact@lupindental.com>
Maintainer-email: LupinDental <contact@lupindental.com>
Project-URL: Repository, https://gitlab.com/lupindental/arsene/devops/sonarcloud_report
Classifier: Programming Language :: Python :: 3.10
Classifier: Programming Language :: Python :: 3.11
Classifier: Programming Language :: Python :: 3.12
Classifier: Development Status :: 3 - Alpha
Requires-Python: >=3.10
License-File: LICENCE
Requires-Dist: jinja2 ==3.1.4
Requires-Dist: python-sonarqube-api ==2.0.5
Requires-Dist: typer ==0.12.3
Provides-Extra: dev
Requires-Dist: coverage ; extra == 'dev'
Requires-Dist: pytest ; extra == 'dev'
